README.rst
setup.py
djorm_expressions/__init__.py
djorm_expressions/base.py
djorm_expressions/models.py
djorm_expressions/tree.py
djorm_expressions/utils.py
djorm_expressions/tests/__init__.py
djorm_expressions/tests/models.py
djorm_ext_expressions.egg-info/PKG-INFO
djorm_ext_expressions.egg-info/SOURCES.txt
djorm_ext_expressions.egg-info/dependency_links.txt
djorm_ext_expressions.egg-info/not-zip-safe
djorm_ext_expressions.egg-info/requires.txt
djorm_ext_expressions.egg-info/top_level.txt